setup.cfg
setup.py
src/__init__.py
src/log.py
src/virtualhermit.py
virtualhermit.egg-info/PKG-INFO
virtualhermit.egg-info/SOURCES.txt
virtualhermit.egg-info/dependency_links.txt
virtualhermit.egg-info/entry_points.txt
virtualhermit.egg-info/requires.txt
virtualhermit.egg-info/top_level.txt