Metadata-Version: 1.0
Name: virtualhermit
Version: 0.1.0
Summary: virtualhermit checks your newsfeed before you waste time on it.
Home-page: http://github.com/lakshaykalbhor/virtualhermit
Author: Lakshay Kalbhor
Author-email: lakshaykalbhor@gmail.com
License: MIT
Keywords: facebook,git,github,command line,cli,hermit
Platform: UNKNOWN
